ai_context_core/__init__.py
ai_context_core/cli.py
ai_context_core/analyzer/aggregator.py
ai_context_core/analyzer/ai_recommendations.py
ai_context_core/analyzer/antipatterns.py
ai_context_core/analyzer/ast_entry_points.py
ai_context_core/analyzer/ast_metrics.py
ai_context_core/analyzer/ast_qgis.py
ai_context_core/analyzer/ast_security.py
ai_context_core/analyzer/ast_utils.py
ai_context_core/analyzer/ast_visitors.py
ai_context_core/analyzer/complexity_visitor.py
ai_context_core/analyzer/constants.py
ai_context_core/analyzer/dependencies.py
ai_context_core/analyzer/engine.py
ai_context_core/analyzer/fs_utils.py
ai_context_core/analyzer/git_analysis.py
ai_context_core/analyzer/graph_engine.py
ai_context_core/analyzer/html_builder.py
ai_context_core/analyzer/ignore_filter.py
ai_context_core/analyzer/import_visitor.py
ai_context_core/analyzer/issues.py
ai_context_core/analyzer/metrics.py
ai_context_core/analyzer/pattern_utils.py
ai_context_core/analyzer/patterns.py
ai_context_core/analyzer/reporting.py
ai_context_core/analyzer/secrets.py
ai_context_core/analyzer/summary_generator.py
ai_context_core/analyzer/antipattern_detectors/__init__.py
ai_context_core/analyzer/antipattern_detectors/base.py
ai_context_core/analyzer/antipattern_detectors/dead_code.py
ai_context_core/analyzer/antipattern_detectors/god_object.py
ai_context_core/analyzer/antipattern_detectors/magic_number.py
ai_context_core/analyzer/antipattern_detectors/spaghetti_code.py
ai_context_core/analyzer/checkers/__init__.py
ai_context_core/analyzer/checkers/optimization_checker.py
ai_context_core/analyzer/checkers/security_checker.py
ai_context_core/analyzer/checkers/tech_debt_checker.py
ai_context_core/analyzer/patterns_detectors/__init__.py
ai_context_core/analyzer/patterns_detectors/base.py
ai_context_core/analyzer/patterns_detectors/decorator.py
ai_context_core/analyzer/patterns_detectors/factory.py
ai_context_core/analyzer/patterns_detectors/observer.py
ai_context_core-3.0.1.dist-info/licenses/LICENSE
ai_context_core-3.0.1.dist-info/METADATA
ai_context_core-3.0.1.dist-info/WHEEL
ai_context_core-3.0.1.dist-info/entry_points.txt
ai_context_core-3.0.1.dist-info/top_level.txt
ai_context_core-3.0.1.dist-info/RECORD
