Metadata-Version: 2.4
Name: ai-context-core
Version: 3.0.1
Summary: Core logic for AI-driven development context management
Author-email: "Juan M. Bernales" <juanbernales@gmail.com>
License: GPL-3.0-or-later
Project-URL: Repository, https://github.com/geociencio/ai-context-core
Project-URL: Issues, https://github.com/geociencio/ai-context-core/issues
Project-URL: Documentation, https://github.com/geociencio/ai-context-core/blob/main/README.md
Keywords: ai,context,llm,analysis,development-tools,productivity
Classifier: Development Status :: 4 - Beta
Classifier: Intended Audience :: Developers
Classifier: Topic :: Software Development :: Libraries :: Python Modules
Classifier: License :: OSI Approved :: GNU General Public License v3 (GPLv3)
Classifier: Programming Language :: Python :: 3
Classifier: Programming Language :: Python :: 3.9
Classifier: Programming Language :: Python :: 3.10
Classifier: Programming Language :: Python :: 3.11
Classifier: Programming Language :: Python :: 3.12
Classifier: Operating System :: OS Independent
Requires-Python: >=3.9
License-File: LICENSE
Requires-Dist: click>=8.0
Requires-Dist: rich>=13.0
Dynamic: license-file
